slurry_websocket/__init__.py
slurry_websocket/websocket.py
slurry_websocket-0.4.2.dist-info/LICENSE
slurry_websocket-0.4.2.dist-info/WHEEL
slurry_websocket-0.4.2.dist-info/METADATA
slurry_websocket-0.4.2.dist-info/RECORD
